odoo/addons/account_fiscal_position_allowed_journal/README.rst
odoo/addons/account_fiscal_position_allowed_journal/__init__.py
odoo/addons/account_fiscal_position_allowed_journal/__manifest__.py
odoo/addons/account_fiscal_position_allowed_journal/i18n/account_fiscal_position_allowed_journal.pot
odoo/addons/account_fiscal_position_allowed_journal/i18n/fr.po
odoo/addons/account_fiscal_position_allowed_journal/models/__init__.py
odoo/addons/account_fiscal_position_allowed_journal/models/account_fiscal_position.py
odoo/addons/account_fiscal_position_allowed_journal/models/account_move.py
odoo/addons/account_fiscal_position_allowed_journal/readme/CONFIGURE.rst
odoo/addons/account_fiscal_position_allowed_journal/readme/CONTRIBUTORS.rst
odoo/addons/account_fiscal_position_allowed_journal/readme/DESCRIPTION.rst
odoo/addons/account_fiscal_position_allowed_journal/readme/USAGE.rst
odoo/addons/account_fiscal_position_allowed_journal/static/description/icon.png
odoo/addons/account_fiscal_position_allowed_journal/static/description/index.html
odoo/addons/account_fiscal_position_allowed_journal/tests/__init__.py
odoo/addons/account_fiscal_position_allowed_journal/tests/test_account_fiscal_position_allowed_journal.py
odoo/addons/account_fiscal_position_allowed_journal/views/account_fiscal_position.xml
odoo13_addon_account_fiscal_position_allowed_journal-13.0.1.0.1.dev4.dist-info/METADATA
odoo13_addon_account_fiscal_position_allowed_journal-13.0.1.0.1.dev4.dist-info/WHEEL
odoo13_addon_account_fiscal_position_allowed_journal-13.0.1.0.1.dev4.dist-info/top_level.txt
odoo13_addon_account_fiscal_position_allowed_journal-13.0.1.0.1.dev4.dist-info/RECORD
