Metadata-Version: 2.1
Name: odoo13-addon-account-fiscal-position-allowed-journal
Version: 13.0.1.0.1.dev4
Summary: Allow defining allowed journals on fiscal positions. Related invoices can only use one of the allowed journals on the fiscal position.
Home-page: https://github.com/OCA/account-financial-tools
Author: ACSONE SA/NV, Odoo Community Association (OCA)
Author-email: support@odoo-community.org
License: AGPL-3
Platform: UNKNOWN
Classifier: Programming Language :: Python
Classifier: Framework :: Odoo
Classifier: Framework :: Odoo :: 13.0
Classifier: License :: OSI Approved :: GNU Affero General Public License v3
Classifier: Development Status :: 4 - Beta
Requires-Python: >=3.5
Requires-Dist: odoo <13.1dev,>=13.0a
